Metadata-Version: 2.1
Name: seedguard-beta
Version: 0.0.1
Summary: Poisoning Functionalities for your dataset
Author: Prabhanjan Vinoda Bharadwaj
Author-email: prabhanjan.vb03@gmail.com
Keywords: python,poison,badcode,codesearch,defense,attack
Classifier: Development Status :: 1 - Planning
Classifier: Intended Audience :: Developers
Classifier: Programming Language :: Python :: 3
Classifier: Operating System :: Unix
Classifier: Operating System :: MacOS :: MacOS X
Classifier: Operating System :: Microsoft :: Windows
License-File: LICENSE
